AUTHORS.md
CHANGELOG.md
CONTRIBUTING.md
LICENSE
MANIFEST.in
README.md
setup.cfg
setup.py
docs/Makefile
docs/conf.py
docs/make.bat
ebr_trackerbot/__init__.py
ebr_trackerbot/bot.py
ebr_trackerbot/checker.py
ebr_trackerbot/cli.py
ebr_trackerbot/module_loader.py
ebr_trackerbot/state.py
ebr_trackerbot/time_utility.py
ebr_trackerbot.egg-info/PKG-INFO
ebr_trackerbot.egg-info/SOURCES.txt
ebr_trackerbot.egg-info/dependency_links.txt
ebr_trackerbot.egg-info/entry_points.txt
ebr_trackerbot.egg-info/not-zip-safe
ebr_trackerbot.egg-info/requires.txt
ebr_trackerbot.egg-info/top_level.txt
ebr_trackerbot/command/__init__.py
ebr_trackerbot/command/help.py
ebr_trackerbot/command/list.py
ebr_trackerbot/command/show.py
ebr_trackerbot/command/track.py
ebr_trackerbot/command/untrack.py
ebr_trackerbot/storage/__init__.py
ebr_trackerbot/storage/db.py
ebr_trackerbot/storage/odbc.py
ebr_trackerbot/storage/sqlite.py
tests/__init__.py
tests/conftest.py
tests/integration/__init__.py
tests/integration/test_storage.py
tests/unit/__init__.py
tests/unit/test_checker.py
tests/unit/test_cli.py
tests/unit/test_command_help.py
tests/unit/test_command_list.py
tests/unit/test_command_show.py
tests/unit/test_command_track.py
tests/unit/test_command_untrack.py
tests/unit/test_configuration.py
tests/unit/test_ebr_trackerbot.py
tests/unit/test_storage_db.py