Metadata-Version: 2.1
Name: ebr-trackerbot
Version: 0.1.4
Summary: EBR Tracker Slack Bot
Home-page: https://github.com/tomtom-international/ebr-trackerbot
Author: Milan Hradil
Author-email: milan.hradil@tomtom.com
License: Apache Software License 2.0
Keywords: ebr_trackerbot
Platform: UNKNOWN
Classifier: Development Status :: 3 - Alpha
Classifier: Intended Audience :: Developers
Classifier: License :: OSI Approved :: Apache Software License
Classifier: Natural Language :: English
Classifier: Programming Language :: Python :: 3
Classifier: Programming Language :: Python :: 3.6
Classifier: Programming Language :: Python :: 3.7
